<?xml version="1.0" encoding="utf-8" ?>
<Deposit>
  <lblTitle><![CDATA[Gửi Tiền Nhanh]]></lblTitle>
  <lblDepositAmount><![CDATA[Số Tiền Gửi]]></lblDepositAmount>
  <lblReferenceId><![CDATA[Số Tham Chiếu]]></lblReferenceId>
  <lblSystemAccount><![CDATA[Hệ Thống Tài Khoản]]></lblSystemAccount>
  <drpSystemAccount><![CDATA[Hệ Thống Tài Khoản Lựa Chọn]]></drpSystemAccount>
  <drpDepositDateTime><![CDATA[Ngày/ Giờ Gửi Tiền]]></drpDepositDateTime>
  <lblDepositChannel><![CDATA[Phương Thức Gửi Tiền]]></lblDepositChannel>
  <drpDepositChannel><![CDATA[Phương Thức Gửi Tiền Lựa Chọn]]></drpDepositChannel>
  <lblBank><![CDATA[Ngân Hàng]]></lblBank>
  <drpBank><![CDATA[Ngân Hàng Lựa Chọn]]></drpBank>
  <lblBankName><![CDATA[Tên Ngân Hàng]]></lblBankName>
  <drpOtherBank><![CDATA[Ngân Hàng Khác]]></drpOtherBank>
  <lblAccountName><![CDATA[Tên Tài Khoản Ngân Hàng]]></lblAccountName>
  <lblAccountNumber><![CDATA[Số Tài Khoản Ngân Hàng]]></lblAccountNumber>
  <btnSubmit><![CDATA[GỬI TIỀN]]></btnSubmit>
  <lblTransactionId><![CDATA[Mã Số Giao Dịch]]></lblTransactionId>
  <lblDailyLimit><![CDATA[Giới Hạn Trong Ngày: ]]></lblDailyLimit>
  <lblTotalAllowed><![CDATA[Tổng Số Cho Phép: ]]></lblTotalAllowed>
  <unlimited><![CDATA[Không giới hạn]]></unlimited>

  <DepositChannel>
    <ATM><![CDATA[ATM]]></ATM>
    <iBanking><![CDATA[Chuyển Khoản Trên Ngân Hàng Trực Tuyến]]></iBanking>
    <mBanking><![CDATA[Chuyển Khoản Trên Di Động]]></mBanking>
    <cBanking><![CDATA[Chuyển Tiền Tại Quầy]]></cBanking>
    <CDM><![CDATA[Chuyển Tiền Mặt Qua Máy ATM]]></CDM>
  </DepositChannel>

  <BankNameNative>
    <ZH-CN_RMB />
    <VI-VN_VND />
    <TH-TH_THB />
    <ID-ID_IDR />
    <KM-KH_USD />
    <KO-KR_KRW />
    <JA-JP_JPY />
  </BankNameNative>
  
  <Calendar>
    <m1><![CDATA[Jan]]></m1>
    <m2><![CDATA[Feb]]></m2>
    <m3><![CDATA[Mar]]></m3>
    <m4><![CDATA[Apr]]></m4>
    <m5><![CDATA[May]]></m5>
    <m6><![CDATA[Jun]]></m6>
    <m7><![CDATA[Jul]]></m7>
    <m8><![CDATA[Aug]]></m8>
    <m9><![CDATA[Sep]]></m9>
    <m10><![CDATA[Oct]]></m10>
    <m11><![CDATA[Nov]]></m11>
    <m12><![CDATA[Dec]]></m12>
  </Calendar>
</Deposit>