<?xml version="1.0" encoding="utf-8" ?>
<default>
	<Products>
		<ASports>
			<Url><![CDATA[]]></Url>
			<Label><![CDATA[东方体育]]></Label>
			<Description><![CDATA[最佳亚洲视角体育投注现已登陆！]]></Description>
		</ASports>
		<ESports>
			<Url><![CDATA[]]></Url>
			<Label><![CDATA[西方体育]]></Label>
			<Description><![CDATA[最佳亚欧混合视角体育投注现已登陆！]]></Description>
		</ESports>
		<Poker>
			<Url><![CDATA[]]></Url>
			<Label><![CDATA[扑克]]></Label>
			<Description><![CDATA[扑克]]></Description>
		</Poker>
		<texasmahjong>
			<Url><![CDATA[]]></Url>
			<Label><![CDATA[德州麻将]]></Label>
			<Description><![CDATA[德州麻将]]></Description>
		</texasmahjong>
		<ISports>
			<Url><![CDATA[]]></Url>
			<Label><![CDATA[爱体育]]></Label>
			<Description><![CDATA[Sportsbook]]></Description>
		</ISports>
		<USports>
			<Url><![CDATA[]]></Url>
			<Label><![CDATA[优体育]]></Label>
			<Description><![CDATA[Sportsbook]]></Description>
		</USports>
		<VSports>
			<Url><![CDATA[]]></Url>
			<Label><![CDATA[虚拟体育]]></Label>
			<Description><![CDATA[基于全真实数据，高频体育投注全天24小时无间隙！]]></Description>
			<Notice><![CDATA[*** 不支持IE浏览器和火狐浏览器 ***]]></Notice>
		</VSports>
		<VSports-basketball>
			<Url><![CDATA[]]></Url>
			<Label><![CDATA[篮球]]></Label>
			<Description><![CDATA[Sportsbook]]></Description>
		</VSports-basketball>
		<VSports-tennis>
			<Url><![CDATA[]]></Url>
			<Label><![CDATA[网球]]></Label>
			<Description><![CDATA[Sportsbook]]></Description>
		</VSports-tennis>
		<VSports-horseracing>
			<Url><![CDATA[]]></Url>
			<Label><![CDATA[赛马]]></Label>
			<Description><![CDATA[Sportsbook]]></Description>
		</VSports-horseracing>
		<VSports-football>
			<Url><![CDATA[]]></Url>
			<Label><![CDATA[足球]]></Label>
			<Description><![CDATA[Sportsbook]]></Description>
		</VSports-football>
		<VSports-dogracing>
			<Url><![CDATA[]]></Url>
			<Label><![CDATA[赛狗]]></Label>
			<Description><![CDATA[Sportsbook]]></Description>
		</VSports-dogracing>
		<Lottery>
			<Url><![CDATA[]]></Url>
			<Label><![CDATA[乐透]]></Label>
			<Description><![CDATA[快乐彩和分分乐]]></Description>
		</Lottery>
		<Keno>
			<Url><![CDATA[]]></Url>
			<Label><![CDATA[快乐彩]]></Label>
			<Description><![CDATA[快乐彩和分分乐]]></Description>
		</Keno>
		<ClubCrescendo>
			<Url><![CDATA[]]></Url>
			<Label><![CDATA[金弦]]></Label>
			<Description><![CDATA[金弦俱乐部]]></Description>
		</ClubCrescendo>
		<ClubDivino>
			<Url><![CDATA[]]></Url>
			<Label><![CDATA[金梵]]></Label>
			<Description><![CDATA[金池俱乐部3D]]></Description>
		</ClubDivino>
		<ClubW>
			<Url><![CDATA[]]></Url>
			<Label><![CDATA[优德俱乐部]]></Label>
			<Description><![CDATA[]]></Description>
		</ClubW>
		<ClubWPremier>
			<Url><![CDATA[]]></Url>
			<Label><![CDATA[优德俱乐部 - 卓越厅]]></Label>
			<Description><![CDATA[]]></Description>
		</ClubWPremier>
		<ClubBravado>
			<Url><![CDATA[]]></Url>
			<Label><![CDATA[金池]]></Label>
			<Description><![CDATA[]]></Description>
		</ClubBravado>
		<ClubMassimoSlots>
			<Url><![CDATA[]]></Url>
			<Label><![CDATA[金銮]]></Label>
			<Description><![CDATA[]]></Description>
		</ClubMassimoSlots>
		<ClubMassimoSlots2>
			<Url><![CDATA[]]></Url>
			<Label><![CDATA[金銮 下载]]></Label>
			<Description><![CDATA[]]></Description>
		</ClubMassimoSlots2>
		<ClubMassimoCasino>
			<Url><![CDATA[]]></Url>
			<Label><![CDATA[金銮]]></Label>
			<Description><![CDATA[]]></Description>
		</ClubMassimoCasino>
		<ClubPalazzoSlots>
			<Url><![CDATA[]]></Url>
			<Label><![CDATA[金殿]]></Label>
			<Description><![CDATA[]]></Description>
		</ClubPalazzoSlots>
		<ClubPalazzoSlots2>
			<Url><![CDATA[]]></Url>
			<Label><![CDATA[金殿 下载]]></Label>
			<Description><![CDATA[]]></Description>
		</ClubPalazzoSlots2>
		<ClubPalazzoCasino>
			<Url><![CDATA[]]></Url>
			<Label><![CDATA[金殿]]></Label>
			<Description><![CDATA[]]></Description>
		</ClubPalazzoCasino>
		<ClubGallardo>
			<Url><![CDATA[]]></Url>
			<Label><![CDATA[金樽俱乐部]]></Label>
			<Description><![CDATA[]]></Description>
		</ClubGallardo>
		<ClubApollo>
			<Url><![CDATA[]]></Url>
			<Label><![CDATA[金帝]]></Label>
			<Description><![CDATA[]]></Description>
		</ClubApollo>
		<ClubNuovo>
			<Url><![CDATA[]]></Url>
			<Label><![CDATA[金蟾]]></Label>
			<Description><![CDATA[]]></Description>
		</ClubNuovo>
	</Products>
	<Wallets>
		<main><![CDATA[中心钱包]]></main>
		<asports><![CDATA[东方体育]]></asports>
		<esports><![CDATA[西方体育]]></esports>
		<isports><![CDATA[爱体育]]></isports>
		<lottery><![CDATA[乐透]]></lottery>
		<casino><![CDATA[优德俱乐部(真人+其他老虎机俱乐部),乐透]]></casino>
		<liveCasino><![CDATA[真人娱乐城]]></liveCasino>
		<playtech><![CDATA[金殿(PT真人+老虎机)]]></playtech>
		<binary><![CDATA[金融]]></binary>
		<poker><![CDATA[扑克]]></poker>
		<sbtech><![CDATA[西方体育]]></sbtech>
		<netent><![CDATA[金蟾]]></netent>
		<pmahjong><![CDATA[德州麻将]]></pmahjong>
	</Wallets>
	<Popup>
		<Palazzo>
			<SafariTitle><![CDATA[简单几步轻松使用Safari浏览器畅玩金殿俱乐部]]></SafariTitle>
			<SafariSettings><![CDATA[在Safari浏览器中的设置：]]></SafariSettings>
			<SafariBlockPopup><![CDATA[阻止弹出式窗口: 关闭]]></SafariBlockPopup>
			<SafariDoNotTrack><![CDATA[不跟踪: 关闭]]></SafariDoNotTrack>
			<SafariBlockCookies><![CDATA[阻止Cookie: 始终允许]]></SafariBlockCookies>
		</Palazzo>
		<DoNotShow><![CDATA[下次登录不在显示]]></DoNotShow>
	</Popup>
</default>
